markdown_figure_caption/__init__.py
markdown_figure_caption-0.0.1.dist-info/DESCRIPTION.rst
markdown_figure_caption-0.0.1.dist-info/METADATA
markdown_figure_caption-0.0.1.dist-info/RECORD
markdown_figure_caption-0.0.1.dist-info/WHEEL
markdown_figure_caption-0.0.1.dist-info/metadata.json
markdown_figure_caption-0.0.1.dist-info/top_level.txt
